escapepath.py
escapepath-0.1.0.dist-info/licenses/LICENSE
escapepath-0.1.0.dist-info/METADATA
escapepath-0.1.0.dist-info/WHEEL
escapepath-0.1.0.dist-info/top_level.txt
escapepath-0.1.0.dist-info/RECORD
