Metadata-Version: 2.4
Name: escapepath
Version: 0.1.0
Summary: A lightweight Python utility to safely escape file paths for command-line usage.
Author-email: Jifeng Wu <jifengwu2k@gmail.com>
License-Expression: MIT
Project-URL: Homepage, https://github.com/jifengwu2k/escapepath
Project-URL: Bug Tracker, https://github.com/jifengwu2k/escapepath/issues
Classifier: Programming Language :: Python
Classifier: Operating System :: OS Independent
Requires-Python: >=2
License-File: LICENSE
Dynamic: license-file
